{
  "relationships_permanent_follow_requests": [
    {
      "title": "",
      "media_list_data": [
        
      ],
      "string_list_data": [
        {
          "href": "https://www.instagram.com/jprodrigues.x",
          "value": "jprodrigues.x",
          "timestamp": 1652756923
        }
      ]
    },
    {
      "title": "",
      "media_list_data": [
        
      ],
      "string_list_data": [
        {
          "href": "https://www.instagram.com/joaodore",
          "value": "joaodore",
          "timestamp": 1651934436
        }
      ]
    },
    {
      "title": "",
      "media_list_data": [
        
      ],
      "string_list_data": [
        {
          "href": "https://www.instagram.com/lourenco_teseu",
          "value": "lourenco_teseu",
          "timestamp": 1651277375
        }
      ]
    },
    {
      "title": "",
      "media_list_data": [
        
      ],
      "string_list_data": [
        {
          "href": "https://www.instagram.com/lucascorpe93",
          "value": "lucascorpe93",
          "timestamp": 1651277367
        }
      ]
    },
    {
      "title": "",
      "media_list_data": [
        
      ],
      "string_list_data": [
        {
          "href": "https://www.instagram.com/isaque.gadelha",
          "value": "isaque.gadelha",
          "timestamp": 1650555215
        }
      ]
    },
    {
      "title": "",
      "media_list_data": [
        
      ],
      "string_list_data": [
        {
          "href": "https://www.instagram.com/_gabrielallm",
          "value": "_gabrielallm",
          "timestamp": 1649954269
        }
      ]
    },
    {
      "title": "",
      "media_list_data": [
        
      ],
      "string_list_data": [
        {
          "href": "https://www.instagram.com/diogo_nogueira.l",
          "value": "diogo_nogueira.l",
          "timestamp": 1649877794
        }
      ]
    },
    {
      "title": "",
      "media_list_data": [
        
      ],
      "string_list_data": [
        {
          "href": "https://www.instagram.com/ana_beatriz.freitas567",
          "value": "ana_beatriz.freitas567",
          "timestamp": 1648425496
        }
      ]
    },
    {
      "title": "",
      "media_list_data": [
        
      ],
      "string_list_data": [
        {
          "href": "https://www.instagram.com/euevoce_ateofim",
          "value": "euevoce_ateofim",
          "timestamp": 1648250843
        }
      ]
    },
    {
      "title": "",
      "media_list_data": [
        
      ],
      "string_list_data": [
        {
          "href": "https://www.instagram.com/marcioguimaraes06",
          "value": "marcioguimaraes06",
          "timestamp": 1648068534
        }
      ]
    }
  ]
}